crouton/__init__.py
crouton/_version.py
crouton/core/__init__.py
crouton/core/_base.py
crouton/core/_types.py
crouton/core/_utils.py
crouton/core/databases.py
crouton/core/mem.py
crouton/core/sqlalchemy.py
crouton/py.typed
crouton-0.1.6.dist-info/METADATA
crouton-0.1.6.dist-info/WHEEL
crouton-0.1.6.dist-info/RECORD
